MANIFEST.in
README
VERSION
setup.py
bin/scalr
scalr.egg-info/PKG-INFO
scalr.egg-info/SOURCES.txt
scalr.egg-info/dependency_links.txt
scalr.egg-info/requires.txt
scalr.egg-info/top_level.txt
scalrtools/__init__.py
scalrtools/cli.py
scalrtools/collections_.py
scalrtools/commands.py
scalrtools/config.py
scalrtools/api/__init__.py
scalrtools/api/client.py
scalrtools/api/types_.py
scalrtools/api/view.py