Metadata-Version: 1.1
Name: scalr
Version: 0.3.64
Summary: Scalr-tools is a command-line interface to your Scalr account
Home-page: https://scalr.net
Author: Scalr Inc.
Author-email: dmitry@scalr.com
License: GPL
Platform: any
Classifier: Programming Language :: Python
Classifier: Programming Language :: Python :: 2
Classifier: License :: OSI Approved :: GNU General Public License (GPL)
Classifier: Operating System :: OS Independent
Classifier: Development Status :: 4 - Beta
Classifier: Environment :: Console
Classifier: Intended Audience :: System Administrators
Classifier: Topic :: Utilities
